pyjod/__init__.py
pyjod-0.0.2.dist-info/Licence.txt
pyjod-0.0.2.dist-info/METADATA
pyjod-0.0.2.dist-info/WHEEL
pyjod-0.0.2.dist-info/top_level.txt
pyjod-0.0.2.dist-info/RECORD
