Metadata-Version: 2.1
Name: pyjod
Version: 0.0.2
Summary: Aoa 2nd year Package
Author: Godfather
License: UNKNOWN
Platform: UNKNOWN
License-File: Licence.txt
